f5teem/__init__.py
f5teem/anonymous_device_client.py
f5teem/constants.py
f5teem/exceptions.py
f5teem/utils/__init__.py
f5teem/utils/http_utils.py
f5_teem-1.0.2.dist-info/LICENSE
f5_teem-1.0.2.dist-info/METADATA
f5_teem-1.0.2.dist-info/WHEEL
f5_teem-1.0.2.dist-info/top_level.txt
f5_teem-1.0.2.dist-info/RECORD
