Metadata-Version: 2.1
Name: f5-teem
Version: 1.0.2
Summary: F5 TEEM Library
Home-page: UNKNOWN
Author: F5 Ecosystems Group
Author-email: solutionsfeedback@f5.com
License: Apache License 2.0
Platform: UNKNOWN
Requires-Dist: requests (>=2)
